[{"owner":"bukunmialuko","repoName":"flutter_ui_kit_obkm","description":"100+ Mobile & Web UI Kit","programmingLanguage":"Dart","programmingLanguageColor":"#00B4AB","totalStars":371,"starsSince":"","totalForks":136,"topContributors":[{"name":"bukunmialuko","avatar":"https://avatars.githubusercontent.com/u/28612861?s=40&v=4"},{"name":"mikkyboy2005","avatar":"https://avatars.githubusercontent.com/u/49166296?s=40&v=4"},{"name":"mbamidele29","avatar":"https://avatars.githubusercontent.com/u/76434119?s=40&v=4"}]},{"owner":"firebase","repoName":"flutterfire","description":"🔥 A collection of Firebase plugins for Flutter apps.","programmingLanguage":"Dart","programmingLanguageColor":"#00B4AB","totalStars":6379,"starsSince":"","totalForks":3128,"topContributors":[{"name":"Salakar","avatar":"https://avatars.githubusercontent.com/u/5347038?s=40&v=4"},{"name":"russellwheatley","avatar":"https://avatars.githubusercontent.com/u/16018629?s=40&v=4"},{"name":"collinjackson","avatar":"https://avatars.githubusercontent.com/u/394889?s=40&v=4"},{"name":"kroikie","avatar":"https://avatars.githubusercontent.com/u/2370200?s=40&v=4"},{"name":"Ehesp","avatar":"https://avatars.githubusercontent.com/u/842078?s=40&v=4"}]},{"owner":"jonataslaw","repoName":"getx","description":"Open screens/snackbars/dialogs/bottomSheets without context, manage states and inject dependencies easily with Get.","programmingLanguage":"Dart","programmingLanguageColor":"#00B4AB","totalStars":6258,"starsSince":"","totalForks":989,"topContributors":[{"name":"jonataslaw","avatar":"https://avatars.githubusercontent.com/u/35742643?s=40&v=4"},{"name":"Nipodemos","avatar":"https://avatars.githubusercontent.com/u/11494727?s=40&v=4"},{"name":"RenatFakhrutdinov","avatar":"https://avatars.githubusercontent.com/u/39668394?s=40&v=4"},{"name":"ahmednfwela","avatar":"https://avatars.githubusercontent.com/u/63286031?s=40&v=4"},{"name":"roipeker","avatar":"https://avatars.githubusercontent.com/u/33768711?s=40&v=4"}]},{"owner":"alibaba","repoName":"flutter_boost","description":"FlutterBoost is a Flutter plugin which enables hybrid integration of Flutter for your existing native apps with minimum efforts","programmingLanguage":"Dart","programmingLanguageColor":"#00B4AB","totalStars":5858,"starsSince":"","totalForks":1012,"topContributors":[{"name":"noborder","avatar":"https://avatars.githubusercontent.com/u/4577931?s=40&v=4"},{"name":"0xZOne","avatar":"https://avatars.githubusercontent.com/u/26625149?s=40&v=4"},{"name":"nightwolf-chen","avatar":"https://avatars.githubusercontent.com/u/2551915?s=40&v=4"},{"name":"ColdPaleLight","avatar":"https://avatars.githubusercontent.com/u/31977171?s=40&v=4"},{"name":"luckysmg","avatar":"https://avatars.githubusercontent.com/u/49340347?s=40&v=4"}]},{"owner":"MaikuB","repoName":"flutter_local_notifications","description":"A Flutter plugin for displaying local notifications on Android, iOS, macOS and Linux","programmingLanguage":"Dart","programmingLanguageColor":"#00B4AB","totalStars":1833,"starsSince":"","totalForks":893,"topContributors":[{"name":"MaikuB","avatar":"https://avatars.githubusercontent.com/u/25263378?s=40&v=4"},{"name":"proninyaroslav","avatar":"https://avatars.githubusercontent.com/u/7840559?s=40&v=4"},{"name":"jeffscaturro-aka","avatar":"https://avatars.githubusercontent.com/u/3655571?s=40&v=4"},{"name":"javiercbk","avatar":"https://avatars.githubusercontent.com/u/1448426?s=40&v=4"},{"name":"byrdkm17","avatar":"https://avatars.githubusercontent.com/u/219080?s=40&v=4"}]},{"owner":"pauldemarco","repoName":"flutter_blue","description":"Bluetooth plugin for Flutter","programmingLanguage":"Dart","programmingLanguageColor":"#00B4AB","totalStars":1997,"starsSince":"","totalForks":1049,"topContributors":[{"name":"pauldemarco","avatar":"https://avatars.githubusercontent.com/u/16725750?s=40&v=4"},{"name":"ened","avatar":"https://avatars.githubusercontent.com/u/269860?s=40&v=4"},{"name":"ezamagni","avatar":"https://avatars.githubusercontent.com/u/6697707?s=40&v=4"},{"name":"lidongze91","avatar":"https://avatars.githubusercontent.com/u/15127060?s=40&v=4"},{"name":"bsheen","avatar":"https://avatars.githubusercontent.com/u/24929993?s=40&v=4"}]},{"owner":"imaNNeoFighT","repoName":"fl_chart","description":"FL Chart is a highly customizable Flutter chart library that supports Line Chart, Bar Chart, Pie Chart, Scatter Chart, and Radar Chart.","programmingLanguage":"Dart","programmingLanguageColor":"#00B4AB","totalStars":4304,"starsSince":"","totalForks":1075,"topContributors":[{"name":"imaNNeoFighT","avatar":"https://avatars.githubusercontent.com/u/7009300?s=40&v=4"},{"name":"shamilovtim","avatar":"https://avatars.githubusercontent.com/u/3495974?s=40&v=4"},{"name":"payam-zahedi","avatar":"https://avatars.githubusercontent.com/u/47558577?s=40&v=4"},{"name":"prajwal27wiijii","avatar":"https://avatars.githubusercontent.com/u/95603936?s=40&v=4"},{"name":"jrc2139","avatar":"https://avatars.githubusercontent.com/u/999564?s=40&v=4"}]},{"owner":"flutter","repoName":"plugins","description":"Plugins for Flutter maintained by the Flutter team","programmingLanguage":"Dart","programmingLanguageColor":"#00B4AB","totalStars":15377,"starsSince":"","totalForks":8699,"topContributors":[{"name":"stuartmorgan","avatar":"https://avatars.githubusercontent.com/u/122189?s=40&v=4"},{"name":"cyanglaz","avatar":"https://avatars.githubusercontent.com/u/3756895?s=40&v=4"},{"name":"collinjackson","avatar":"https://avatars.githubusercontent.com/u/394889?s=40&v=4"},{"name":"jmagman","avatar":"https://avatars.githubusercontent.com/u/682784?s=40&v=4"},{"name":"bparrishMines","avatar":"https://avatars.githubusercontent.com/u/10687576?s=40&v=4"}]},{"owner":"flutter","repoName":"samples","description":"A collection of Flutter examples and demos","programmingLanguage":"Dart","programmingLanguageColor":"#00B4AB","totalStars":11417,"starsSince":"","totalForks":5029,"topContributors":[{"name":"domesticmouse","avatar":"https://avatars.githubusercontent.com/u/30503?s=40&v=4"},{"name":"RedBrogdon","avatar":"https://avatars.githubusercontent.com/u/969662?s=40&v=4"},{"name":"johnpryan","avatar":"https://avatars.githubusercontent.com/u/1145719?s=40&v=4"},{"name":"kevmoo","avatar":"https://avatars.githubusercontent.com/u/17034?s=40&v=4"},{"name":"rami-a","avatar":"https://avatars.githubusercontent.com/u/2364772?s=40&v=4"}]},{"owner":"rrousselGit","repoName":"river_pod","description":"A simple way to access state while robust and testable.","programmingLanguage":"Dart","programmingLanguageColor":"#00B4AB","totalStars":2656,"starsSince":"","totalForks":399,"topContributors":[{"name":"rrousselGit","avatar":"https://avatars.githubusercontent.com/u/20165741?s=40&v=4"},{"name":"dependabot","avatar":"https://avatars.githubusercontent.com/in/29110?s=40&v=4"},{"name":"TimWhiting","avatar":"https://avatars.githubusercontent.com/u/15617545?s=40&v=4"},{"name":"tbm98","avatar":"https://avatars.githubusercontent.com/u/52562340?s=40&v=4"},{"name":"mono0926","avatar":"https://avatars.githubusercontent.com/u/1255062?s=40&v=4"}]},{"owner":"flutter","repoName":"flutter","description":"Flutter makes it easy and fast to build beautiful apps for mobile and beyond","programmingLanguage":"Dart","programmingLanguageColor":"#00B4AB","totalStars":137712,"starsSince":"","totalForks":21188,"topContributors":[{"name":"engine-flutter-autoroll","avatar":"https://avatars.githubusercontent.com/u/42042535?s=40&v=4"},{"name":"abarth","avatar":"https://avatars.githubusercontent.com/u/112007?s=40&v=4"},{"name":"Hixie","avatar":"https://avatars.githubusercontent.com/u/551196?s=40&v=4"},{"name":"jonahwilliams","avatar":"https://avatars.githubusercontent.com/u/8975114?s=40&v=4"},{"name":"HansMuller","avatar":"https://avatars.githubusercontent.com/u/1377460?s=40&v=4"}]},{"owner":"Solido","repoName":"awesome-flutter","description":"An awesome list that curates the best Flutter libraries, tools, tutorials, articles and more.","programmingLanguage":"Dart","programmingLanguageColor":"#00B4AB","totalStars":39872,"starsSince":"","totalForks":5844,"topContributors":[{"name":"Solido","avatar":"https://avatars.githubusercontent.com/u/1295961?s=40&v=4"},{"name":"jogboms","avatar":"https://avatars.githubusercontent.com/u/6208486?s=40&v=4"},{"name":"vintage","avatar":"https://avatars.githubusercontent.com/u/729785?s=40&v=4"},{"name":"lijy91","avatar":"https://avatars.githubusercontent.com/u/3889523?s=40&v=4"},{"name":"TatsuUkraine","avatar":"https://avatars.githubusercontent.com/u/621542?s=40&v=4"}]},{"owner":"alesimula","repoName":"wsa_pacman","description":"A GUI package manager and package installer for Windows Subsystem for Android (WSA)","programmingLanguage":"Dart","programmingLanguageColor":"#00B4AB","totalStars":1362,"starsSince":"","totalForks":264,"topContributors":[{"name":"alesimula","avatar":"https://avatars.githubusercontent.com/u/3057584?s=40&v=4"},{"name":"madrichim","avatar":"https://avatars.githubusercontent.com/u/97272923?s=40&v=4"},{"name":"wcxu21","avatar":"https://avatars.githubusercontent.com/u/86864914?s=40&v=4"},{"name":"FullyRealist","avatar":"https://avatars.githubusercontent.com/u/90242919?s=40&v=4"},{"name":"igorruckert","avatar":"https://avatars.githubusercontent.com/u/3202395?s=40&v=4"}]},{"owner":"Lyokone","repoName":"flutterlocation","description":"A Flutter plugin to easily handle realtime location in iOS and Android. Provides settings for optimizing performance or battery.","programmingLanguage":"Dart","programmingLanguageColor":"#00B4AB","totalStars":865,"starsSince":"","totalForks":505,"topContributors":[{"name":"Lyokone","avatar":"https://avatars.githubusercontent.com/u/3680002?s=40&v=4"},{"name":"mehmetf","avatar":"https://avatars.githubusercontent.com/u/6687929?s=40&v=4"},{"name":"long1eu","avatar":"https://avatars.githubusercontent.com/u/9283414?s=40&v=4"},{"name":"Alexays","avatar":"https://avatars.githubusercontent.com/u/13947260?s=40&v=4"},{"name":"kevlatus","avatar":"https://avatars.githubusercontent.com/u/9928134?s=40&v=4"}]},{"owner":"ResoCoder","repoName":"flutter-tdd-clean-architecture-course","description":"","programmingLanguage":"Dart","programmingLanguageColor":"#00B4AB","totalStars":1343,"starsSince":"","totalForks":462,"topContributors":[{"name":"ResoDev","avatar":"https://avatars.githubusercontent.com/u/18404788?s=40&v=4"},{"name":"ricardoebbers","avatar":"https://avatars.githubusercontent.com/u/20364528?s=40&v=4"}]},{"owner":"jhomlala","repoName":"betterplayer","description":"Better video player for Flutter, with multiple configuration options. Solving typical use cases!","programmingLanguage":"Dart","programmingLanguageColor":"#00B4AB","totalStars":573,"starsSince":"","totalForks":344,"topContributors":[{"name":"jhomlala","avatar":"https://avatars.githubusercontent.com/u/1329033?s=40&v=4"},{"name":"jhomlalabsg","avatar":"https://avatars.githubusercontent.com/u/67579018?s=40&v=4"},{"name":"ganeshrvel","avatar":"https://avatars.githubusercontent.com/u/182092?s=40&v=4"},{"name":"themadmrj","avatar":"https://avatars.githubusercontent.com/u/11475495?s=40&v=4"},{"name":"FlutterSu","avatar":"https://avatars.githubusercontent.com/u/46503636?s=40&v=4"}]},{"owner":"Baseflow","repoName":"flutter-geolocator","description":"Android and iOS Geolocation plugin for Flutter","programmingLanguage":"Dart","programmingLanguageColor":"#00B4AB","totalStars":953,"starsSince":"","totalForks":397,"topContributors":[{"name":"mvanbeusekom","avatar":"https://avatars.githubusercontent.com/u/13098888?s=40&v=4"},{"name":"martijn00","avatar":"https://avatars.githubusercontent.com/u/6221156?s=40&v=4"},{"name":"florissmit1","avatar":"https://avatars.githubusercontent.com/u/47666575?s=40&v=4"},{"name":"Sempakonka","avatar":"https://avatars.githubusercontent.com/u/47318358?s=40&v=4"},{"name":"danielroek","avatar":"https://avatars.githubusercontent.com/u/32639467?s=40&v=4"}]},{"owner":"felangel","repoName":"bloc","description":"A predictable state management library that helps implement the BLoC design pattern","programmingLanguage":"Dart","programmingLanguageColor":"#00B4AB","totalStars":8708,"starsSince":"","totalForks":2548,"topContributors":[{"name":"felangel","avatar":"https://avatars.githubusercontent.com/u/8855632?s=40&v=4"},{"name":"tenhobi","avatar":"https://avatars.githubusercontent.com/u/5287596?s=40&v=4"},{"name":"zepfietje","avatar":"https://avatars.githubusercontent.com/u/44533235?s=40&v=4"},{"name":"Abhishek01039","avatar":"https://avatars.githubusercontent.com/u/56479665?s=40&v=4"},{"name":"mzdm","avatar":"https://avatars.githubusercontent.com/u/67197047?s=40&v=4"}]},{"owner":"rrousselGit","repoName":"provider","description":"InheritedWidgets, but simple","programmingLanguage":"Dart","programmingLanguageColor":"#00B4AB","totalStars":4168,"starsSince":"","totalForks":420,"topContributors":[{"name":"rrousselGit","avatar":"https://avatars.githubusercontent.com/u/20165741?s=40&v=4"},{"name":"robsonsilv4","avatar":"https://avatars.githubusercontent.com/u/17673296?s=40&v=4"},{"name":"enetor","avatar":"https://avatars.githubusercontent.com/u/1323571?s=40&v=4"},{"name":"felangel","avatar":"https://avatars.githubusercontent.com/u/8855632?s=40&v=4"},{"name":"joaomarcos96","avatar":"https://avatars.githubusercontent.com/u/31287923?s=40&v=4"}]},{"owner":"fluttercommunity","repoName":"chewie","description":"The video player for Flutter with a heart of gold","programmingLanguage":"Dart","programmingLanguageColor":"#00B4AB","totalStars":1431,"starsSince":"","totalForks":703,"topContributors":[{"name":"cbenhagen","avatar":"https://avatars.githubusercontent.com/u/814785?s=40&v=4"},{"name":"nstrelow","avatar":"https://avatars.githubusercontent.com/u/1096841?s=40&v=4"},{"name":"Ahmadre","avatar":"https://avatars.githubusercontent.com/u/18512224?s=40&v=4"},{"name":"brianegan","avatar":"https://avatars.githubusercontent.com/u/126604?s=40&v=4"},{"name":"maherjaafar","avatar":"https://avatars.githubusercontent.com/u/34738373?s=40&v=4"}]},{"owner":"alibaba","repoName":"flutter-go","description":"flutter 开发者帮助 APP，包含 flutter 常用 140+ 组件的demo 演示与中文文档","programmingLanguage":"Dart","programmingLanguageColor":"#00B4AB","totalStars":23001,"starsSince":"","totalForks":3710,"topContributors":[{"name":"hanxu317317","avatar":"https://avatars.githubusercontent.com/u/8518989?s=40&v=4"},{"name":"ryan730","avatar":"https://avatars.githubusercontent.com/u/14855190?s=40&v=4"},{"name":"Nealyang","avatar":"https://avatars.githubusercontent.com/u/9313216?s=40&v=4"},{"name":"DeckeDeng","avatar":"https://avatars.githubusercontent.com/u/15521823?s=40&v=4"},{"name":"zymxxxs","avatar":"https://avatars.githubusercontent.com/u/6263633?s=40&v=4"}]},{"owner":"bluefireteam","repoName":"audioplayers","description":"A Flutter plugin to play multiple audio files simultaneously (Android/iOS)","programmingLanguage":"Dart","programmingLanguageColor":"#00B4AB","totalStars":1282,"starsSince":"","totalForks":574,"topContributors":[{"name":"luanpotter","avatar":"https://avatars.githubusercontent.com/u/882703?s=40&v=4"},{"name":"subhash279","avatar":"https://avatars.githubusercontent.com/u/23074764?s=40&v=4"},{"name":"feroult","avatar":"https://avatars.githubusercontent.com/u/455623?s=40&v=4"},{"name":"proteye","avatar":"https://avatars.githubusercontent.com/u/5658532?s=40&v=4"},{"name":"rxlabz","avatar":"https://avatars.githubusercontent.com/u/1397248?s=40&v=4"}]},{"owner":"syncfusion","repoName":"flutter-widgets","description":"Syncfusion Flutter widgets libraries include high quality UI widgets and file-format packages to help you create rich, high-quality applications for iOS, Android, and web from a single code base.","programmingLanguage":"Dart","programmingLanguageColor":"#00B4AB","totalStars":713,"starsSince":"","totalForks":254,"topContributors":[{"name":"JayavigneshwaranG","avatar":"https://avatars.githubusercontent.com/u/19405163?s=40&v=4"},{"name":"Rokesh-Karthikeyan","avatar":"https://avatars.githubusercontent.com/u/79526737?s=40&v=4"},{"name":"dharanidharandharmasivam","avatar":"https://avatars.githubusercontent.com/u/19346074?s=40&v=4"},{"name":"PavithraNandhiniRamachandran","avatar":"https://avatars.githubusercontent.com/u/79507200?s=40&v=4"},{"name":"Yuvaraj-Gajaraj","avatar":"https://avatars.githubusercontent.com/u/61863686?s=40&v=4"}]},{"owner":"abuanwar072","repoName":"E-commerce-App-UI-Flutter","description":"Nice and clean Online Shop app UI by using #Flutter.","programmingLanguage":"Dart","programmingLanguageColor":"#00B4AB","totalStars":1443,"starsSince":"","totalForks":784,"topContributors":[{"name":"abuanwar072","avatar":"https://avatars.githubusercontent.com/u/42710380?s=40&v=4"},{"name":"BishwajitNepali","avatar":"https://avatars.githubusercontent.com/u/10056611?s=40&v=4"},{"name":"alisonjr","avatar":"https://avatars.githubusercontent.com/u/28691546?s=40&v=4"}]},{"owner":"aleksanderwozniak","repoName":"table_calendar","description":"Highly customizable, feature-packed calendar widget for Flutter","programmingLanguage":"Dart","programmingLanguageColor":"#00B4AB","totalStars":1249,"starsSince":"","totalForks":616,"topContributors":[{"name":"aleksanderwozniak","avatar":"https://avatars.githubusercontent.com/u/22658673?s=40&v=4"},{"name":"shamilovtim","avatar":"https://avatars.githubusercontent.com/u/3495974?s=40&v=4"},{"name":"maxgmer","avatar":"https://avatars.githubusercontent.com/u/24964174?s=40&v=4"},{"name":"fstof","avatar":"https://avatars.githubusercontent.com/u/1650553?s=40&v=4"},{"name":"FineFindus","avatar":"https://avatars.githubusercontent.com/u/63370021?s=40&v=4"}]}]